eufy_security/__init__.py
eufy_security/__version__.py
eufy_security/api.py
eufy_security/converters.py
eufy_security/crypto.py
eufy_security/device.py
eufy_security/errors.py
eufy_security/param.py
eufy_security/py.typed
eufy_security/types.py
pyeufysecurity-0.4.3.dist-info/METADATA
pyeufysecurity-0.4.3.dist-info/WHEEL
pyeufysecurity-0.4.3.dist-info/licenses/AUTHORS.md
pyeufysecurity-0.4.3.dist-info/licenses/LICENSE
pyeufysecurity-0.4.3.dist-info/RECORD
