Metadata-Version: 2.4
Name: pyeufysecurity
Version: 0.4.3
Summary: A Python library for Eufy Security cameras and devices
Project-URL: Homepage, https://github.com/ptarjan/pyeufysecurity
Project-URL: Repository, https://github.com/ptarjan/pyeufysecurity
Author-email: Aaron Bach <bachya1208@gmail.com>, Marty Zalega <marty@zalega.me>, Paul Tarjan <github@paulisageek.com>
License-Expression: MIT
License-File: AUTHORS.md
License-File: LICENSE
Classifier: Development Status :: 4 - Beta
Classifier: Intended Audience :: Developers
Classifier: License :: OSI Approved :: MIT License
Classifier: Programming Language :: Python :: 3
Classifier: Programming Language :: Python :: 3.11
Classifier: Programming Language :: Python :: 3.12
Classifier: Programming Language :: Python :: 3.13
Requires-Python: >=3.11
Requires-Dist: aiohttp>=3.0.0
Requires-Dist: cryptography>=41.0.0
